hedgedoc_py/__init__.py
hedgedoc_py/hedgedoc.py
hedgedoc_py-0.1.0.dist-info/WHEEL
hedgedoc_py-0.1.0.dist-info/METADATA
hedgedoc_py-0.1.0.dist-info/RECORD
