Metadata-Version: 2.1
Name: hedgedoc-py
Version: 0.1.0
Summary: Simple wrapper around the HedgeDoc API
License: MIT
Author: JulianSobott
Author-email: julian.sobott@gmail.com
Requires-Python: >=3.9,<4.0
Classifier: License :: OSI Approved :: MIT License
Classifier: Programming Language :: Python :: 3
Classifier: Programming Language :: Python :: 3.10
Classifier: Programming Language :: Python :: 3.9
Requires-Dist: requests (>=2.28.1,<3.0.0)
